{
  "timestamp": "2025-07-27T01:22:19.776805",
  "uptime_seconds": 100497.5,
  "memory": {
    "total_gb": 23.42,
    "available_gb": 19.78,
    "used_gb": 3.26,
    "percent": 15.5,
    "swap_used_gb": 0.0,
    "swap_total_gb": 0.0
  },
  "disk": {
    "total_gb": 44.07,
    "used_gb": 11.82,
    "free_gb": 32.23,
    "percent": 26.83
  },
  "cpu": {
    "percent": 6.3,
    "count": 4,
    "load_1min": 0.6259765625,
    "load_5min": 0.39892578125,
    "load_15min": 0.251953125
  },
  "top_processes": [
    {
      "pid": 345609,
      "name": "node",
      "memory_percent": 4.17,
      "cpu_percent": 3.6
    },
    {
      "pid": 346335,
      "name": "node",
      "memory_percent": 3.21,
      "cpu_percent": 0.0
    },
    {
      "pid": 1486,
      "name": "k3s-server",
      "memory_percent": 2.36,
      "cpu_percent": 4.0
    }
  ],
  "alerts": [],
  "system_healthy": true
}