{
  "timestamp": "2025-07-26T17:54:51.917365",
  "uptime_seconds": 73649.6,
  "memory": {
    "total_gb": 23.42,
    "available_gb": 21.15,
    "used_gb": 1.89,
    "percent": 9.7,
    "swap_used_gb": 0.0,
    "swap_total_gb": 0.0
  },
  "disk": {
    "total_gb": 44.07,
    "used_gb": 11.82,
    "free_gb": 32.24,
    "percent": 26.82
  },
  "cpu": {
    "percent": 0.8,
    "count": 4,
    "load_1min": 0.173828125,
    "load_5min": 0.0859375,
    "load_15min": 0.02001953125
  },
  "top_processes": [
    {
      "pid": 293944,
      "name": "node",
      "memory_percent": 2.53,
      "cpu_percent": 0.0
    },
    {
      "pid": 1486,
      "name": "k3s-server",
      "memory_percent": 2.27,
      "cpu_percent": 4.5
    }
  ],
  "alerts": [],
  "system_healthy": true
}