{
  "timestamp": "2025-07-29T03:44:44.787478",
  "uptime_seconds": 281842.5,
  "memory": {
    "total_gb": 23.42,
    "available_gb": 21.87,
    "used_gb": 1.17,
    "percent": 6.6,
    "swap_used_gb": 0.0,
    "swap_total_gb": 0.0
  },
  "disk": {
    "total_gb": 44.07,
    "used_gb": 12.03,
    "free_gb": 32.02,
    "percent": 27.31
  },
  "cpu": {
    "percent": 0.5,
    "count": 4,
    "load_1min": 0.009765625,
    "load_5min": 0.0458984375,
    "load_15min": 0.044921875
  },
  "top_processes": [
    {
      "pid": 1486,
      "name": "k3s-server",
      "memory_percent": 2.39,
      "cpu_percent": 4.1
    }
  ],
  "alerts": [],
  "system_healthy": true
}